Metadata-Version: 1.0
Name: gafs
Version: 0.0.2
Summary: Genetic algorigthm feature selection.
Home-page: https://github.com/Shemka/GAFS
Author: Alexander Shemchuk
Author-email: sheminy32@gmail.com
License: MIT
Platform: UNKNOWN
